bb/__init__.py
bb/exceptions.py
bb/live_table.py
bb/typeshed.py
bb/utils.py
bb/version.py
bb/cli/__init__.py
bb/cli/alias.py
bb/cli/auth.py
bb/cli/git.py
bb/cli/main.py
bb/cli/pr.py
bb/core/config.py
bb/core/git.py
bb/models/__init__.py
bb/models/base.py
bb/models/filediff.py
bb/models/pullrequest.py
bb/models/repository.py
bb/models/user.py
bb/tui/__init__.py
bb/tui/app.py
bb/tui/state.py
bb/tui/types.py
bb/tui/css/pr_detail.tcss
bb/tui/screens/__init__.py
bb/tui/screens/base.py
bb/tui/screens/pr_detail.py
bb/tui/screens/pr_diff.py
bb/tui/screens/pr_list.py
bb/tui/widgets/__init__.py
bb/tui/widgets/file_diff.py
bb/tui/widgets/live_table.py
bb/tui/widgets/selectable_table.py
bb/tui/widgets/stat_display.py
bitbucket_cloud_cli-0.4.0.dist-info/METADATA
bitbucket_cloud_cli-0.4.0.dist-info/WHEEL
bitbucket_cloud_cli-0.4.0.dist-info/entry_points.txt
bitbucket_cloud_cli-0.4.0.dist-info/licenses/LICENSE
bitbucket_cloud_cli-0.4.0.dist-info/RECORD
