Metadata-Version: 2.3
Name: bitbucket-cloud-cli
Version: 0.4.0
Summary: Atlassian Bitbucket Cloud CLI
Author-email: tjk <tkells@atlassian.com>
Requires-Python: >=3.8
Requires-Dist: arrow>=1.3.0
Requires-Dist: click>=8.1.7
Requires-Dist: ipdb>=0.13.13
Requires-Dist: readchar>=4.1.0
Requires-Dist: requests>=2.32.2
Requires-Dist: rich>=13.7.1
Requires-Dist: textual>=1.0.0
Requires-Dist: tomli-w>=1.0.0
Requires-Dist: tomli>=2.0.1
